binny/__init__.py
binny/_nbdev.py
binny/core.py
pg_binny/__init__.py
pg_binny/_nbdev.py
pg_binny/core.py
pg_binny-0.0.3.dist-info/LICENSE
pg_binny-0.0.3.dist-info/METADATA
pg_binny-0.0.3.dist-info/WHEEL
pg_binny-0.0.3.dist-info/entry_points.txt
pg_binny-0.0.3.dist-info/top_level.txt
pg_binny-0.0.3.dist-info/RECORD
