Metadata-Version: 2.1
Name: pg-binny
Version: 0.0.3
Summary: Bins your dataframe columns into the Top ≤N categories, and "Other".
Home-page: https://gitlab.ausdev.local/peregrine/pg_binny/tree/main/
Author: Charles Twardy
Author-email: Charles.Twardy@jacobs.com
License: Apache Software License 2.0
Keywords: discretize,bin,Python,datascience,preprocess
Platform: UNKNOWN
Classifier: Development Status :: 3 - Alpha
Classifier: Intended Audience :: Developers
Classifier: License :: OSI Approved :: Apache Software License
Classifier: Natural Language :: English
Classifier: Programming Language :: Python :: 3.6
Classifier: Programming Language :: Python :: 3.7
Classifier: Programming Language :: Python :: 3.8
Requires-Python: >=3.6
Requires-Dist: numpy
Requires-Dist: pandas
Requires-Dist: matplotlib
Requires-Dist: scikit-learn
